robin_chat_input/__init__.py
robin_chat_input/frontend/build/asset-manifest.json
robin_chat_input/frontend/build/bootstrap.min.css
robin_chat_input/frontend/build/index.html
robin_chat_input/frontend/build/static/js/2.08b0a941.chunk.js
robin_chat_input/frontend/build/static/js/2.08b0a941.chunk.js.LICENSE.txt
robin_chat_input/frontend/build/static/js/2.08b0a941.chunk.js.map
robin_chat_input/frontend/build/static/js/main.63e3d358.chunk.js
robin_chat_input/frontend/build/static/js/main.63e3d358.chunk.js.map
robin_chat_input/frontend/build/static/js/main.f16661d0.chunk.js
robin_chat_input/frontend/build/static/js/main.f16661d0.chunk.js.map
robin_chat_input/frontend/build/static/js/runtime-main.e6b0ae4c.js
robin_chat_input/frontend/build/static/js/runtime-main.e6b0ae4c.js.map
robin_chat_input-0.0.8.dist-info/LICENSE
robin_chat_input-0.0.8.dist-info/METADATA
robin_chat_input-0.0.8.dist-info/WHEEL
robin_chat_input-0.0.8.dist-info/top_level.txt
robin_chat_input-0.0.8.dist-info/RECORD
