Metadata-Version: 2.1
Name: robin-chat-input
Version: 0.0.8
Home-page: 
Author: Chris Doyle
Author-email: chris@robinai.co.uk
Requires-Python: >=3.6
License-File: LICENSE
Requires-Dist: streamlit (>=0.63)
